jokepy/__init__.py
jokepy-1.0.3.dist-info/LICENSE.txt
jokepy-1.0.3.dist-info/METADATA
jokepy-1.0.3.dist-info/WHEEL
jokepy-1.0.3.dist-info/top_level.txt
jokepy-1.0.3.dist-info/RECORD
