Metadata-Version: 2.1
Name: jokepy
Version: 1.0.3
Summary: A python wrapper for https://sv443.net/jokeapi/v2
Home-page: https://github.com/aksty/Jokepy
Author: Akshay T
Author-email: sup.aks.apps@gmail.com
License: MIT
Platform: UNKNOWN
Classifier: Programming Language :: Python :: 3
Classifier: Operating System :: OS Independent
Requires-Python: >=3.6
Requires-Dist: requests
